pysplit/__init__.py
pysplit/cartodesigner.py
pysplit/clusgroup.py
pysplit/hy_processor.py
pysplit/hyfile_handler.py
pysplit/hygroup.py
pysplit/hypath.py
pysplit/mapdesigner.py
pysplit/maplabeller.py
pysplit/mapmaker.py
pysplit/traj.py
pysplit/trajectory_generator.py
pysplit/trajgroup.py
PySPLIT-0.3.6.dist-info/LICENSE
PySPLIT-0.3.6.dist-info/METADATA
PySPLIT-0.3.6.dist-info/WHEEL
PySPLIT-0.3.6.dist-info/top_level.txt
PySPLIT-0.3.6.dist-info/RECORD
