Metadata-Version: 2.1
Name: PySPLIT
Version: 0.3.6
Summary: HYSPLIT trajectory analysis, automation, & visualization
Home-page: UNKNOWN
Maintainer: Mellissa S. C. Warner
Maintainer-email: mellissa.s.c.warner@gmail.com
License: Modified BSD
Platform: UNKNOWN
Classifier: Development Status :: 4 - Beta
Classifier: Environment :: Console
Classifier: Intended Audience :: Developers
Classifier: Intended Audience :: Science/Research
Classifier: License :: OSI Approved :: BSD License
Classifier: Programming Language :: Python
Classifier: Programming Language :: Python :: 3
Classifier: Topic :: Scientific/Engineering
Classifier: Operating System :: Microsoft :: Windows
Classifier: Operating System :: POSIX
Classifier: Operating System :: Unix
Classifier: Operating System :: MacOS
